CMakeLists.txt
LICENSE
MANIFEST.in
README.md
chatglm.cpp
chatglm.h
chatglm_pybind.cpp
chatglm_test.cpp
main.cpp
pyproject.toml
setup.py
chatglm_cpp/_C.pyi
chatglm_cpp/__init__.py
chatglm_cpp/convert.py
chatglm_cpp/langchain_api.py
chatglm_cpp/openai_api.py
chatglm_cpp.egg-info/PKG-INFO
chatglm_cpp.egg-info/SOURCES.txt
chatglm_cpp.egg-info/dependency_links.txt
chatglm_cpp.egg-info/requires.txt
chatglm_cpp.egg-info/top_level.txt
docs/README.md
tests/test_chatglm_cpp.py
tests/test_convert.py
third_party/abseil-cpp/.clang-format
third_party/abseil-cpp/.git
third_party/abseil-cpp/.gitignore
third_party/abseil-cpp/ABSEIL_ISSUE_TEMPLATE.md
third_party/abseil-cpp/AUTHORS
third_party/abseil-cpp/BUILD.bazel
third_party/abseil-cpp/CMakeLists.txt
third_party/abseil-cpp/CONTRIBUTING.md
third_party/abseil-cpp/FAQ.md
third_party/abseil-cpp/LICENSE
third_party/abseil-cpp/MODULE.bazel
third_party/abseil-cpp/PrivacyInfo.xcprivacy
third_party/abseil-cpp/README.md
third_party/abseil-cpp/UPGRADES.md
third_party/abseil-cpp/WORKSPACE
third_party/abseil-cpp/WORKSPACE.bzlmod
third_party/abseil-cpp/conanfile.py
third_party/abseil-cpp/create_lts.py
third_party/abseil-cpp/.github/PULL_REQUEST_TEMPLATE.md
third_party/abseil-cpp/.github/ISSUE_TEMPLATE/00-bug_report.yml
third_party/abseil-cpp/.github/ISSUE_TEMPLATE/config.yml
third_party/abseil-cpp/CMake/AbseilDll.cmake
third_party/abseil-cpp/CMake/AbseilHelpers.cmake
third_party/abseil-cpp/CMake/README.md
third_party/abseil-cpp/CMake/abslConfig.cmake.in
third_party/abseil-cpp/CMake/Googletest/CMakeLists.txt.in
third_party/abseil-cpp/CMake/Googletest/DownloadGTest.cmake
third_party/abseil-cpp/CMake/install_test_project/CMakeLists.txt
third_party/abseil-cpp/CMake/install_test_project/simple.cc
third_party/abseil-cpp/CMake/install_test_project/test.sh
third_party/abseil-cpp/absl/BUILD.bazel
third_party/abseil-cpp/absl/CMakeLists.txt
third_party/abseil-cpp/absl/abseil.podspec.gen.py
third_party/abseil-cpp/absl/algorithm/BUILD.bazel
third_party/abseil-cpp/absl/algorithm/CMakeLists.txt
third_party/abseil-cpp/absl/algorithm/algorithm.h
third_party/abseil-cpp/absl/algorithm/algorithm_test.cc
