Metadata-Version: 2.1
Name: chatglm-cpp
Version: 0.4.1
Summary: C++ implementation of ChatGLM family models
Author-email: Jiahao Li <liplus17@163.com>
Maintainer-email: Jiahao Li <liplus17@163.com>
License: MIT License
Project-URL: Homepage, https://github.com/li-plus/chatglm.cpp
Project-URL: Repository, https://github.com/li-plus/chatglm.cpp.git
Keywords: ChatGLM,ChatGLM2,ChatGLM3,Large Language Model
Classifier: Development Status :: 3 - Alpha
Classifier: Intended Audience :: Science/Research
Classifier: Topic :: Scientific/Engineering :: Artificial Intelligence
Classifier: License :: OSI Approved :: MIT License
Classifier: Programming Language :: Python :: 3.8
Classifier: Programming Language :: Python :: 3.9
Classifier: Programming Language :: Python :: 3.10
Classifier: Programming Language :: Python :: 3.11
Classifier: Programming Language :: Python :: 3.12
Requires-Python: >=3.7
License-File: LICENSE
Provides-Extra: api
Requires-Dist: fastapi[all]; extra == "api"
Requires-Dist: sse-starlette; extra == "api"
